marfa_bi_connection/__init__.py
marfa_bi_connection/databaseConnection.py
marfa_bi_connection-1.0.5.dist-info/METADATA
marfa_bi_connection-1.0.5.dist-info/WHEEL
marfa_bi_connection-1.0.5.dist-info/top_level.txt
marfa_bi_connection-1.0.5.dist-info/RECORD
