Metadata-Version: 2.1
Name: marfa-bi-connection
Version: 1.0.5
Summary: MarfaBI connections
Home-page: https://github.com/NorddyM/MarfaBI
Author: Ruslan Galimov
Author-email: rgalimov@marfa-tech.com
License: MIT
Classifier: Intended Audience :: Developers
Classifier: License :: OSI Approved :: MIT License
Classifier: Programming Language :: Python
Classifier: Programming Language :: Python :: 3
Classifier: Programming Language :: Python :: 3.6
Classifier: Programming Language :: Python :: 3.7
Classifier: Programming Language :: Python :: 3.8
Classifier: Programming Language :: Python :: 3.9
Classifier: Programming Language :: Python :: 3.10
Classifier: Operating System :: OS Independent
Requires-Dist: PyMySQL
Requires-Dist: PyYAML
Requires-Dist: sshtunnel
Requires-Dist: pandas
Requires-Dist: python-telegram-bot (==13.15)
Requires-Dist: SQLAlchemy
Requires-Dist: clickhouse-sqlalchemy
Requires-Dist: clickhouse-driver
Requires-Dist: google-cloud-bigquery
Requires-Dist: slack-sdk
Requires-Dist: google
Requires-Dist: cryptography
